{"cameraMode":{"drawMode":0,"name":"Shaded","section":"Shading Mode"},"sceneLighting":false,"audioPlay":false,"sceneViewState":{"m_AlwaysRefresh":false,"showFog":true,"showSkybox":false,"showFlares":true,"showImageEffects":true,"showParticleSystems":true,"showVisualEffectGraphs":true,"m_FxEnabled":true},"in2DMode":false,"pivot":{"x":-7.71999979019165,"y":0.0,"z":-6.800000190734863},"rotation":{"x":-0.5156639218330383,"y":0.00822166632860899,"z":-0.004949590191245079,"w":-0.8567374348640442},"size":10.0,"orthographic":false}